pylibvw.so
pyvw.py
pyvw-8.0.0.post1.dist-info/DESCRIPTION.rst
pyvw-8.0.0.post1.dist-info/METADATA
pyvw-8.0.0.post1.dist-info/metadata.json
pyvw-8.0.0.post1.dist-info/pbr.json
pyvw-8.0.0.post1.dist-info/RECORD
pyvw-8.0.0.post1.dist-info/top_level.txt
pyvw-8.0.0.post1.dist-info/WHEEL
