Metadata-Version: 2.0
Name: pyvw
Version: 8.0.0.post1
Summary: The Vowpal Wabbit (VW) project is a fast out-of-core learning system.
Home-page: https://github.com/JohnLangford/vowpal_wabbit
Author: trbs
Author-email: trbs@trbs.net
License: UNKNOWN
Platform: UNKNOWN
Classifier: Development Status :: 3 - Alpha
Classifier: Intended Audience :: Developers
Classifier: License :: OSI Approved :: BSD License
Classifier: Topic :: Scientific/Engineering
